memoir/__init__.py
memoir/cached.py
memoir/hints.py
memoir-0.0.3.dist-info/LICENSE
memoir-0.0.3.dist-info/METADATA
memoir-0.0.3.dist-info/WHEEL
memoir-0.0.3.dist-info/top_level.txt
memoir-0.0.3.dist-info/RECORD
